nv_one_logger/no_init.md
nv_one_logger/training_telemetry/integration/_compat/lightning.py
nv_one_logger/training_telemetry/integration/no_init.md
nv_one_logger/training_telemetry/integration/pytorch_lightning.py
nv_one_logger/training_telemetry/no_init.md
nv_one_logger_pytorch_lightning_integration-2.3.0.dist-info/LICENSE
nv_one_logger_pytorch_lightning_integration-2.3.0.dist-info/METADATA
nv_one_logger_pytorch_lightning_integration-2.3.0.dist-info/WHEEL
nv_one_logger_pytorch_lightning_integration-2.3.0.dist-info/RECORD
