Metadata-Version: 2.1
Name: nv-one-logger-pytorch-lightning-integration
Version: 2.3.0
Summary: Wrappers that facilitate enabling training job telemetry for a set of supported training frameworks.
License: Apache-2.0
Author: HWInf-MLWFO
Author-email: HWInf-MLWFO-E2E-Dev@exchange.nvidia.com
Requires-Python: >=3.9,<3.14
Classifier: License :: OSI Approved :: Apache Software License
Classifier: Programming Language :: Python :: 3
Classifier: Programming Language :: Python :: 3.9
Classifier: Programming Language :: Python :: 3.10
Classifier: Programming Language :: Python :: 3.11
Classifier: Programming Language :: Python :: 3.12
Classifier: Programming Language :: Python :: 3.13
Requires-Dist: StrEnum (>=0.4.0,<0.5.0)
Requires-Dist: lightning (>=2.2.0)
Requires-Dist: nv-one-logger-core (>=2.3.0,<3.0.0)
Requires-Dist: nv-one-logger-training-telemetry (>=2.3.0,<3.0.0)
Requires-Dist: setuptools (>=79.0.0)
